scihub_dmunozg/__init__.py
scihub_dmunozg/run.py
scihub_dmunozg/scihub.py
scihub_dmunozg-0.2.0.dist-info/LICENSE
scihub_dmunozg-0.2.0.dist-info/METADATA
scihub_dmunozg-0.2.0.dist-info/WHEEL
scihub_dmunozg-0.2.0.dist-info/entry_points.txt
scihub_dmunozg-0.2.0.dist-info/RECORD
