Metadata-Version: 2.1
Name: scihub_dmunozg
Version: 0.2.0
Summary: Unofficial API for retrieving documents from SciHub
Author: Diego Muñoz G.
Author-email: diego@asgamers.net
Requires-Python: >=3.11,<4.0
Classifier: Programming Language :: Python :: 3
Classifier: Programming Language :: Python :: 3.11
Classifier: Programming Language :: Python :: 3.12
Requires-Dist: beautifulsoup4 (>=4.12.3,<5.0.0)
Requires-Dist: loguru (>=0.7.2,<0.8.0)
Requires-Dist: pysocks (>=1.7.1,<2.0.0)
Requires-Dist: requests (>=2.31.0,<3.0.0)
Requires-Dist: retrying (>=1.3.4,<2.0.0)
Requires-Dist: scholarly (>=1.7.11,<2.0.0)
Requires-Dist: selenium (>=4.17.2,<5.0.0)
